pitch_detectors/__init__.py
pitch_detectors/config.py
pitch_detectors/schemas.py
pitch_detectors/util.py
pitch_detectors/algorithms/__init__.py
pitch_detectors/algorithms/base.py
pitch_detectors/algorithms/crepe.py
pitch_detectors/algorithms/ensemble.py
pitch_detectors/algorithms/penn.py
pitch_detectors/algorithms/piptrack.py
pitch_detectors/algorithms/praatac.py
pitch_detectors/algorithms/praatcc.py
pitch_detectors/algorithms/praatshs.py
pitch_detectors/algorithms/pyin.py
pitch_detectors/algorithms/rapt.py
pitch_detectors/algorithms/reaper.py
pitch_detectors/algorithms/spice.py
pitch_detectors/algorithms/swipe.py
pitch_detectors/algorithms/torchcrepe.py
pitch_detectors/algorithms/torchyin.py
pitch_detectors/algorithms/world.py
pitch_detectors/algorithms/yaapt.py
pitch_detectors/algorithms/yin.py
pitch_detectors/evaluation/__init__.py
pitch_detectors/evaluation/__main__.py
pitch_detectors/evaluation/table.py
pitch_detectors/evaluation/datasets/__init__.py
pitch_detectors/evaluation/datasets/base.py
pitch_detectors/evaluation/datasets/mdb_stem_synth.py
pitch_detectors/evaluation/datasets/mir_1k.py
scripts/download_models.py
scripts/run_algorithm.py
tests/__init__.py
tests/algorithms_test.py
tests/gpu_test.py
pitch_detectors-0.7.0.dist-info/METADATA
pitch_detectors-0.7.0.dist-info/WHEEL
pitch_detectors-0.7.0.dist-info/top_level.txt
pitch_detectors-0.7.0.dist-info/RECORD
