Metadata-Version: 2.1
Name: pitch-detectors
Version: 0.7.0
Summary: collection of pitch detection algorithms with unified interface
Author-email: Alexander Rodionov <tandav@tandav.me>
Project-URL: source, https://github.com/tandav/pitch-detectors
Project-URL: issues, https://github.com/tandav/pitch-detectors/issues
Project-URL: release notes, https://github.com/tandav/pitch-detectors/releases
Requires-Python: <3.13,>=3.12
Requires-Dist: AMFM-decompy
Requires-Dist: tensorflow
Requires-Dist: tensorflow-hub
Requires-Dist: dsplib==0.10.1
Requires-Dist: librosa
Requires-Dist: scipy==1.14.0
Requires-Dist: numpy>=2.0
Requires-Dist: praat-parselmouth>=0.4.3
Requires-Dist: pyreaper>=0.0.9
Requires-Dist: pysptk
Requires-Dist: pyworld>=0.3.2
Requires-Dist: pydantic>=2.0
Requires-Dist: crepe>=0.0.16
Requires-Dist: resampy==0.4.3
Requires-Dist: torch
Requires-Dist: torch-yin>=0.1.3
Requires-Dist: torchcrepe>=0.0.18
Requires-Dist: penn>=0.0.14
